jianglab/__init__.py
jianglab/common_functions.py
jianglab/params.py
jianglab-1.3.0.dist-info/METADATA
jianglab-1.3.0.dist-info/WHEEL
jianglab-1.3.0.dist-info/top_level.txt
jianglab-1.3.0.dist-info/RECORD
