Metadata-Version: 2.1
Name: jianglab
Version: 1.3.0
Summary: A package for Jiang lab
Home-page: https://github.com/jiang-lab-retina/jianglab.git
Author: Jiang Zheng
Author-email: zjiang314@gmail.com
Classifier: Development Status :: 3 - Alpha
Classifier: License :: OSI Approved :: MIT License
Classifier: Programming Language :: Python :: 3
Classifier: Programming Language :: Python :: 3.6
Classifier: Programming Language :: Python :: 3.7
Classifier: Programming Language :: Python :: 3.8
Classifier: Programming Language :: Python :: 3.9
Classifier: Programming Language :: Python :: 3.10
Classifier: Programming Language :: Python :: 3.11
Requires-Dist: numpy
Requires-Dist: pandas
Requires-Dist: matplotlib
Requires-Dist: treelib ==1.6.4
Requires-Dist: McsPyDataTools
Requires-Dist: tqdm
Requires-Dist: scipy
Requires-Dist: gspread
Requires-Dist: oauth2client
Requires-Dist: xmltodict
Requires-Dist: opencv-python
Requires-Dist: ipython
Requires-Dist: seaborn
Requires-Dist: optuna
Requires-Dist: xgboost
Requires-Dist: scikit-learn
Requires-Dist: umap-learn
Requires-Dist: missingno
